akiFlagger.py
akiFlagger-1.0.10.dist-info/LICENSE.txt
akiFlagger-1.0.10.dist-info/METADATA
akiFlagger-1.0.10.dist-info/WHEEL
akiFlagger-1.0.10.dist-info/top_level.txt
akiFlagger-1.0.10.dist-info/RECORD
