Metadata-Version: 2.1
Name: akiFlagger
Version: 1.0.10
Summary: Flag patients with acute kidney injury as per the KDIGO guidelines.
Home-page: https://github.com/isaranwrap/StandardizingAKI
License: UNKNOWN
Project-URL: Documentation, https://akiflagger.readthedocs.io/en/latest/
Platform: UNKNOWN
Classifier: Programming Language :: Python :: 3
Classifier: Programming Language :: Python :: 3.6
Classifier: Programming Language :: Python :: 3.7
Classifier: License :: OSI Approved :: MIT License
Classifier: Operating System :: OS Independent
Requires-Dist: numpy
Requires-Dist: pandas
